MANIFEST.in
README.md
setup.cfg
setup.py
docstr2argparse/__init__.py
docstr2argparse/parse.py
docstr2argparse.egg-info/PKG-INFO
docstr2argparse.egg-info/SOURCES.txt
docstr2argparse.egg-info/dependency_links.txt
docstr2argparse.egg-info/top_level.txt