Metadata-Version: 1.1
Name: docstr2argparse
Version: 0.0.2
Summary: Automatically generate CLI from a docstring.
Home-page: https://github.com/MatteoLacki/docstr2argparse.git
Author: Mateusz Krzysztof Łącki
Author-email: matteo.lacki@gmail.com
License: UNKNOWN
Keywords: docstring parser
Platform: UNKNOWN
Classifier: Development Status :: 1 - Planning
Classifier: License :: OSI Approved :: BSD License
Classifier: Programming Language :: Python :: 3.6
Classifier: Programming Language :: Python :: 3.7
Classifier: Programming Language :: Python :: 3.8
